tests/__init__.py
tests/test_text_scrubber.py
tests/geo/__init__.py
tests/geo/test_clean.py
tests/geo/test_find_in_string.py
tests/geo/test_normalize.py
tests/geo/test_resources.py
tests/geo/test_string_distance.py
tests/geo/test_string_distance_levenshtein.py
tests/geo/test_string_distance_trigrams.py
text_scrubber/__init__.py
text_scrubber/io.py
text_scrubber/text_scrubber.py
text_scrubber/geo/__init__.py
text_scrubber/geo/clean.py
text_scrubber/geo/find_in_string.py
text_scrubber/geo/normalize.py
text_scrubber/geo/overlap_c.pyx
text_scrubber/geo/overlap_c.pyxbld
text_scrubber/geo/resources.py
text_scrubber/geo/string_distance.py
text_scrubber/geo/string_distance_levenshtein.py
text_scrubber/geo/string_distance_trigrams.py
text_scrubber/geo/resources/country_map.txt
text_scrubber/geo/resources/country_norm_country_map.json
text_scrubber/geo/resources/norm_country_country_codes_map.json
text_scrubber/geo/resources/cities_per_country/AD.txt
text_scrubber/geo/resources/cities_per_country/AE.txt
text_scrubber/geo/resources/cities_per_country/AF.txt
text_scrubber/geo/resources/cities_per_country/AG.txt
text_scrubber/geo/resources/cities_per_country/AI.txt
text_scrubber/geo/resources/cities_per_country/AL.txt
text_scrubber/geo/resources/cities_per_country/AM.txt
text_scrubber/geo/resources/cities_per_country/AN.txt
text_scrubber/geo/resources/cities_per_country/AO.txt
text_scrubber/geo/resources/cities_per_country/AQ.txt
text_scrubber/geo/resources/cities_per_country/AR.txt
text_scrubber/geo/resources/cities_per_country/AS.txt
text_scrubber/geo/resources/cities_per_country/AT.txt
text_scrubber/geo/resources/cities_per_country/AU.txt
text_scrubber/geo/resources/cities_per_country/AW.txt
text_scrubber/geo/resources/cities_per_country/AX.txt
text_scrubber/geo/resources/cities_per_country/AZ.txt
text_scrubber/geo/resources/cities_per_country/BA.txt
text_scrubber/geo/resources/cities_per_country/BB.txt
text_scrubber/geo/resources/cities_per_country/BD.txt
text_scrubber-0.5.0.dist-info/LICENSE
text_scrubber-0.5.0.dist-info/METADATA
text_scrubber-0.5.0.dist-info/WHEEL
text_scrubber-0.5.0.dist-info/top_level.txt
text_scrubber-0.5.0.dist-info/RECORD
