Metadata-Version: 2.1
Name: text-scrubber
Version: 0.5.0
Summary: Python package that offers text scrubbing functionality, providing building blocks for string cleaning as well as normalizing geographical text (countries/states/cities)
Home-page: https://github.com/sybrenjansen/text-scrubber
Author: Sybren Jansen
License: MIT
Classifier: Development Status :: 5 - Production/Stable
Classifier: Programming Language :: Python :: 3.8
Classifier: Programming Language :: Python :: 3.9
Classifier: Programming Language :: Python :: 3.10
Classifier: Programming Language :: Python :: 3.11
Classifier: Programming Language :: Python :: 3.12
Classifier: License :: OSI Approved :: MIT License
Classifier: Topic :: Text Processing
License-File: LICENSE
Requires-Dist: anyascii
Requires-Dist: cython
Requires-Dist: ftfy
Requires-Dist: num2words
Requires-Dist: numpy
Requires-Dist: pylatexenc
Requires-Dist: rapidfuzz
Requires-Dist: scipy
Requires-Dist: setuptools
Requires-Dist: tqdm
Provides-Extra: docs
Requires-Dist: sphinx<6,>=5; extra == "docs"
Requires-Dist: sphinx-rtd-theme==0.5.0; extra == "docs"
Requires-Dist: sphinx-autodoc-typehints==1.11.0; extra == "docs"
Requires-Dist: sphinx-versions==1.0.1; extra == "docs"
Requires-Dist: click==8.0.4; extra == "docs"
Provides-Extra: tests
Requires-Dist: nose2; extra == "tests"
Requires-Dist: numpy; extra == "tests"
